kedro_onnx/__init__.py
kedro_onnx/typing.py
kedro_onnx/utils.py
kedro_onnx/inference/__init__.py
kedro_onnx/inference/inference.py
kedro_onnx/io/__init__.py
kedro_onnx/io/datasets.py
kedro_onnx-0.1.2.dist-info/LICENSE
kedro_onnx-0.1.2.dist-info/METADATA
kedro_onnx-0.1.2.dist-info/WHEEL
kedro_onnx-0.1.2.dist-info/top_level.txt
kedro_onnx-0.1.2.dist-info/RECORD
